<mvc:View controllerName="iot.singleplanningcalendar.controller.SinglePlanningCalendar"
	xmlns="sap.m"
	xmlns:unified="sap.ui.unified"
	xmlns:form="sap.ui.layout.form"
	xmlns:core="sap.ui.core"
	xmlns:smartfield="sap.ui.comp.smartfield"
	xmlns:mvc="sap.ui.core.mvc" displayBlock="true">
	<Shell id="shell">
		<App id="app" busy="{/busy}" busyIndicatorDelay="0">
			<pages>
				<Page showHeader="false">
					<SinglePlanningCalendar id="SPCalendar" appointments="{/appointments}" appointmentSelect="onPressAppointment" cellPress="onCellPress" startDateChange="onStartDateChange" viewChange="onChangeView" startHour="7" endHour="20" fullDay="false">
						<actions>
							<Button id="createAppointment" text="{i18n>createAppointment.button.text}" press="onCreateAppointment" tooltip="{i18n>createAppointment.button.tooltip}" />
						</actions>
						<appointments>
							<unified:CalendarAppointment startDate="{activatedDate}" endDate="{completedDate}" title="{ticket} {title}" text="{customer_ID} {project_ID}" type="{parts: ['type', 'project_ID', 'status'], formatter: '.formatter.getDisplayType'}" icon="{path: 'customer_ID', formatter: '.formatter.getIconURL'}"/>
						</appointments>
						<dependents>
							<Dialog id="createItemDialog" title="Create new entry" binding="{/appointment}">
								<buttons>
									<Button text="OK" type="Emphasized" press="onSubmitEntry"/>
									<Button press="onCloseDialog" text="Close"/>
								</buttons>
								<form:SimpleForm editable="true" layout="ResponsiveGridLayout">
									<Label text="Title"/>
									<Input value="{title}"/>
									<Label text="Customer"/>
									<ComboBox selectedKey="{customer_ID}" items="{/customers}" change="onChangeSelectedCustomer">
										<items>
											<core:Item text="{name}" key="{ID}"/>
										</items>
									</ComboBox>
									<Label text="Project"/>
									<Select selectedKey="{project_ID}" items="{/appointment/customer/projects}" forceSelection="true" change="onChangeSelectedProject">
										<items>
											<core:Item text="{title}" key="{ID}"/>
										</items>
									</Select>
									<Label text="Ticket"/>
									<Input value="{ticket}"/>
									<Label text="Begin"/>
									<DateTimePicker value="{path:'activatedDate', type:'sap.ui.model.type.DateTime', formatOptions: {style: 'medium'}}" />
									<Label text="Completed"/>
									<DateTimePicker value="{path: 'completedDate', type:'sap.ui.model.type.DateTime', formatOptions: {style: 'medium'}}"/>
								</form:SimpleForm>
							</Dialog>
						</dependents>
						<views>
							<SinglePlanningCalendarDayView id="dayView" key="DayView" title="Day" />
							<SinglePlanningCalendarWorkWeekView key="WorkWeekView" title="Work Week" />
							<SinglePlanningCalendarWeekView key="WeekView" title="Week" />
							<SinglePlanningCalendarMonthView id="monthView" key="MonthView" title="Month" />
						</views>
					</SinglePlanningCalendar>
				</Page>
			</pages>
		</App>
	</Shell>
</mvc:View>